pandaprosumer/__init__.py
pandaprosumer/constants.py
pandaprosumer/create.py
pandaprosumer/create_controlled.py
pandaprosumer/pandaprosumer_container.py
pandaprosumer/prosumer_toolbox.py
pandaprosumer/run_control.py
pandaprosumer/run_time_series.py
pandaprosumer/controller/__init__.py
pandaprosumer/controller/base.py
pandaprosumer/controller/const_profile.py
pandaprosumer/controller/mapped.py
pandaprosumer/controller/data_model/__init__.py
pandaprosumer/controller/data_model/base_controller.py
pandaprosumer/controller/data_model/booster_heat_pump.py
pandaprosumer/controller/data_model/booster_heat_pump_sdewes.py
pandaprosumer/controller/data_model/chiller.py
pandaprosumer/controller/data_model/const_profile.py
pandaprosumer/controller/data_model/dry_cooler.py
pandaprosumer/controller/data_model/electric_boiler.py
pandaprosumer/controller/data_model/gas_boiler.py
pandaprosumer/controller/data_model/heat_demand.py
pandaprosumer/controller/data_model/heat_exchanger.py
pandaprosumer/controller/data_model/heat_pump.py
pandaprosumer/controller/data_model/heat_storage.py
pandaprosumer/controller/data_model/ice_chp.py
pandaprosumer/controller/data_model/stratified_heat_storage.py
pandaprosumer/controller/models/__init__.py
pandaprosumer/controller/models/booster_heat_pump.py
pandaprosumer/controller/models/booster_heat_pump_sdewes.py
pandaprosumer/controller/models/chiller.py
pandaprosumer/controller/models/dry_cooler.py
pandaprosumer/controller/models/electric_boiler.py
pandaprosumer/controller/models/gas_boiler.py
pandaprosumer/controller/models/heat_demand.py
pandaprosumer/controller/models/heat_exchanger.py
pandaprosumer/controller/models/heat_pump.py
pandaprosumer/controller/models/heat_storage.py
pandaprosumer/controller/models/ice_chp.py
pandaprosumer/controller/models/stratified_heat_storage.py
pandaprosumer/element/__init__.py
pandaprosumer/element/booster_heat_pump.py
pandaprosumer/element/chiller.py
pandaprosumer/element/const_profile.py
pandaprosumer-0.1.2.dist-info/licenses/AUTHORS
pandaprosumer-0.1.2.dist-info/licenses/LICENSE
pandaprosumer-0.1.2.dist-info/METADATA
pandaprosumer-0.1.2.dist-info/WHEEL
pandaprosumer-0.1.2.dist-info/top_level.txt
pandaprosumer-0.1.2.dist-info/RECORD
