Metadata-Version: 2.4
Name: pandaprosumer
Version: 0.1.2
Summary: A prosumer simulation tool that complements pandapower and pandapipes in the simulation of multi energy systems
Author-email: Pratikshya Mohanty <pratikshya.mohanty@iee.fraunhofer.de>, Erik Prade <erik.prade@iee.fraunhofer.de>
License: Copyright (c) 2025 by Fraunhofer Institute for Energy Economics
Project-URL: Documentation, https://pandaprosumer.readthedocs.io
Project-URL: Source, https://github.com/e2nIEE/pandaprosumer
Project-URL: Repository, https://github.com/e2nIEE/pandaprosumer.git
Project-URL: Issues, https://github.com/e2nIEE/pandaprosumer/issues
Project-URL: Download, https://pypi.org/project/pandaprosumer/#files
Project-URL: Changelog, https://github.com/e2nIEE/pandaprosumer/blob/develop/CHANGELOG.rst
Keywords: prosumer,analysis,controller,automation,grid,energy,engineering,simulation,flexiblity,system
Classifier: Development Status :: 5 - Production/Stable
Classifier: Environment :: Console
Classifier: Intended Audience :: Developers
Classifier: Intended Audience :: Education
Classifier: Intended Audience :: Science/Research
Classifier: License :: OSI Approved :: BSD License
Classifier: Natural Language :: English
Classifier: Operating System :: OS Independent
Classifier: Programming Language :: Python
Classifier: Programming Language :: Python :: 3
Classifier: Programming Language :: Python :: 3.10
Classifier: Programming Language :: Python :: 3.11
Requires-Python: <3.12,>=3.10
License-File: LICENSE
License-File: AUTHORS
Requires-Dist: astral==3.2
Requires-Dist: converter==1.0.0
Requires-Dist: matplotlib>=3.8.0
Requires-Dist: numpy>=1.25.0
Requires-Dist: pandapipes==0.11.0
Requires-Dist: pandapower==2.14.11
Requires-Dist: pandas==2.0.2
Requires-Dist: savReaderWriter==3.4.2
Requires-Dist: scipy>=1.11.0
Requires-Dist: seaborn==0.12.2
Requires-Dist: simbench==1.4.0
Requires-Dist: tqdm==4.65.0
Requires-Dist: numba==0.59.1
Requires-Dist: openpyxl==3.1.5
Requires-Dist: sphinx-pyproject
Requires-Dist: CoolProp==6.7.0
Requires-Dist: pyomo==6.6.1
Requires-Dist: pytest==8.3.3
Provides-Extra: docs
Requires-Dist: numpydoc>=1.5.0; extra == "docs"
Requires-Dist: sphinx>=5.3.0; extra == "docs"
Requires-Dist: sphinx_rtd_theme>=1.1.1; extra == "docs"
Requires-Dist: sphinxcontrib.bibtex>=2.5.0; extra == "docs"
Requires-Dist: sphinx-pyproject; extra == "docs"
Provides-Extra: plotting
Requires-Dist: plotly; extra == "plotting"
Requires-Dist: igraph; extra == "plotting"
Provides-Extra: test
Requires-Dist: pytest==8.3.3; extra == "test"
Requires-Dist: pytest-xdist; extra == "test"
Requires-Dist: pytest-split; extra == "test"
Requires-Dist: nbmake; extra == "test"
Requires-Dist: numba; extra == "test"
Requires-Dist: setuptools; python_version >= "3.10" and extra == "test"
Provides-Extra: all
Requires-Dist: numpydoc>=1.5.0; extra == "all"
Requires-Dist: sphinx>=5.3.0; extra == "all"
Requires-Dist: sphinx_rtd_theme>=1.1.1; extra == "all"
Requires-Dist: sphinxcontrib.bibtex>=2.5.0; extra == "all"
Requires-Dist: sphinx-pyproject; extra == "all"
Requires-Dist: plotly; extra == "all"
Requires-Dist: igraph; extra == "all"
Requires-Dist: pytest; extra == "all"
Requires-Dist: pytest-xdist; extra == "all"
Requires-Dist: pytest-split; extra == "all"
Requires-Dist: nbmake; extra == "all"
Requires-Dist: numba; extra == "all"
Requires-Dist: setuptools; python_version >= "3.10" and extra == "all"
Dynamic: license-file
